Workbook
Name Slicer_Category: #N/A
Name Slicer_Region: #N/A
Name Slicer_Store_Format: #N/A

Sheet Dashboard
A1: FreshMart Retail Waste & Markdown Analytics
A4: Executive Dashboard | Synthetic Portfolio Dataset | January–June 2026
A10: TOTAL REVENUE | B10: TOTAL REVENUE | C10: TOTAL REVENUE | D10: GROSS PROFIT | E10: GROSS PROFIT | F10: GROSS PROFIT | G10: TOTAL LOSS | H10: TOTAL LOSS | I10: TOTAL LOSS | J10: MARKDOWN RECOVERY | K10: MARKDOWN RECOVERY | L10: MARKDOWN RECOVERY | M10: SUPPLIER FILL RATE | N10: SUPPLIER FILL RATE | O10: SUPPLIER FILL RATE | P10: HIGH-RISK STOCK | Q10: HIGH-RISK STOCK | R10: HIGH-RISK STOCK
A11: TOTAL REVENUE | B11: TOTAL REVENUE | C11: TOTAL REVENUE | D11: GROSS PROFIT | E11: GROSS PROFIT | F11: GROSS PROFIT | G11: TOTAL LOSS | H11: TOTAL LOSS | I11: TOTAL LOSS | J11: MARKDOWN RECOVERY | K11: MARKDOWN RECOVERY | L11: MARKDOWN RECOVERY | M11: SUPPLIER FILL RATE | N11: SUPPLIER FILL RATE | O11: SUPPLIER FILL RATE | P11: HIGH-RISK STOCK | Q11: HIGH-RISK STOCK | R11: HIGH-RISK STOCK
A12: ='Pivot Analysis'!B4 -> 4864.58 | B12: 58749.19 | C12: 58749.19 | D12: ='Pivot Analysis'!C4 -> 1705.54 | E12: 20072.43 | F12: 20072.43 | G12: ='Pivot Analysis'!B25 -> 207.36 | H12: 20072.43 | I12: 20072.43 | J12: ='Pivot Analysis'!J42 -> 0.44687779 | K12: 20072.43 | L12: 20072.43 | M12: =GETPIVOTDATA("[Measures].[Supplier Fill Rate %]",'Dashboard Support'!$A$19) -> 0.94227269 | N12: 0.94227269 | O12: 0.94227269 | P12: =SUM('Pivot Analysis'!C72:C76) -> 894 | Q12: 1835 | R12: 1835
A13: 58749.19 | B13: 58749.19 | C13: 58749.19 | D13: 20072.43 | E13: 20072.43 | F13: 20072.43 | G13: 20072.43 | H13: 20072.43 | I13: 20072.43 | J13: 20072.43 | K13: 20072.43 | L13: 20072.43 | M13: 0.94227269 | N13: 0.94227269 | O13: 0.94227269 | P13: 1835 | Q13: 1835 | R13: 1835
A14: Jan–Jun 2026 | B14: Jan–Jun 2026 | C14: Jan–Jun 2026 | D14: =TEXT(D12/A12,"0.0%")&" Gross Margin" -> 35.1% Gross Margin | E14: 34.2% margin | F14: 34.2% margin | G14: =TEXT(G12/A12,"0.0%")&" of revenue" -> 4.3% of revenue | H14: 13.9% of revenue | I14: 13.9% of revenue | J14: ="Sell-through: "&TEXT('Pivot Analysis'!H42,"0.0%") -> Sell-through: 60.0% | K14: Early markdown: 61.4% | L14: Early markdown: 61.4% | M14: ="Short supply: "&TEXT(GETPIVOTDATA("[Measures].[Short-Supply Rate %]",'Dashboard Support'!$A$19),"0.0%") -> Short supply: 5.8% | N14: Short supply: 5.8% | O14: Short supply: 5.8% | P14: Latest inventory snapshot | Q14: Latest inventory snapshot | R14: Latest inventory snapshot
A16: SALES PERFORMANCE | B16: SALES PERFORMANCE | C16: SALES PERFORMANCE | D16: SALES PERFORMANCE | E16: SALES PERFORMANCE | F16: SALES PERFORMANCE | G16: SALES PERFORMANCE | H16: SALES PERFORMANCE | I16: SALES PERFORMANCE | J16: REGIONAL PERFORMANCE | K16: REGIONAL PERFORMANCE | L16: REGIONAL PERFORMANCE | M16: REGIONAL PERFORMANCE | N16: REGIONAL PERFORMANCE | O16: REGIONAL PERFORMANCE | P16: REGIONAL PERFORMANCE | Q16: REGIONAL PERFORMANCE | R16: REGIONAL PERFORMANCE
A47: KEY BUSINESS ACTIONS
A48: 1 | B48: 1 | C48: Reduce Meat & Seafood losses | D48: Reduce Meat & Seafood losses | E48: Reduce Meat & Seafood losses | F48: Reduce Meat & Seafood losses | G48: Reduce Meat & Seafood losses | H48: Reduce Meat & Seafood losses | I48: Meat & Seafood contributes $4,658, representing approximately 57.1% of total loss value. | J48: This category contributes 57.1% of total loss value. | K48: This category contributes 57.1% of total loss value. | L48: This category contributes 57.1% of total loss value. | M48: This category contributes 57.1% of total loss value. | N48: This category contributes 57.1% of total loss value. | O48: This category contributes 57.1% of total loss value. | P48: This category contributes 57.1% of total loss value. | Q48: This category contributes 57.1% of total loss value. | R48: This category contributes 57.1% of total loss value.
A49: 2 | B49: 2 | C49: Move markdown decisions earlier | D49: Move markdown decisions earlier | E49: Move markdown decisions earlier | F49: Move markdown decisions earlier | G49: Move markdown decisions earlier | H49: Move markdown decisions earlier | I49: Early markdown sell-through is 71.6% versus 44.0% for late markdowns. | J49: Early markdown sell-through is 71.6% versus 44.0% for late markdowns. | K49: Early markdown sell-through is 71.6% versus 44.0% for late markdowns. | L49: Early markdown sell-through is 71.6% versus 44.0% for late markdowns. | M49: Early markdown sell-through is 71.6% versus 44.0% for late markdowns. | N49: Early markdown sell-through is 71.6% versus 44.0% for late markdowns. | O49: Early markdown sell-through is 71.6% versus 44.0% for late markdowns. | P49: Early markdown sell-through is 71.6% versus 44.0% for late markdowns. | Q49: Early markdown sell-through is 71.6% versus 44.0% for late markdowns. | R49: Early markdown sell-through is 71.6% versus 44.0% for late markdowns.
A50: 3 | B50: 3 | C50: Focus on the West region | D50: Review supplier exceptions | E50: Review supplier exceptions | F50: Review supplier exceptions | G50: Review supplier exceptions | H50: Review supplier exceptions | I50: The West generates $17,786, accounting for approximately 30.3% of total revenue. | J50: Everyday Grocery Wholesale has the lowest fill rate at 92.6%. | K50: Everyday Grocery Wholesale has the lowest fill rate at 92.6%. | L50: Everyday Grocery Wholesale has the lowest fill rate at 92.6%. | M50: Everyday Grocery Wholesale has the lowest fill rate at 92.6%. | N50: Everyday Grocery Wholesale has the lowest fill rate at 92.6%. | O50: Everyday Grocery Wholesale has the lowest fill rate at 92.6%. | P50: Everyday Grocery Wholesale has the lowest fill rate at 92.6%. | Q50: Everyday Grocery Wholesale has the lowest fill rate at 92.6%. | R50: Everyday Grocery Wholesale has the lowest fill rate at 92.6%.
A51: 4 | B51: 4 | C51: Review supplier exceptions | D51: Prioritise expiry-risk stock | E51: Prioritise expiry-risk stock | F51: Prioritise expiry-risk stock | G51: Prioritise expiry-risk stock | H51: Prioritise expiry-risk stock | I51: Everyday Grocery Wholesale has the lowest fill rate at 92.6%, while Polar Frozen Logistics has the highest average delay. | J51: 1,835 units are currently classified as high expiry risk. | K51: 1,835 units are currently classified as high expiry risk. | L51: 1,835 units are currently classified as high expiry risk. | M51: 1,835 units are currently classified as high expiry risk. | N51: 1,835 units are currently classified as high expiry risk. | O51: 1,835 units are currently classified as high expiry risk. | P51: 1,835 units are currently classified as high expiry risk. | Q51: 1,835 units are currently classified as high expiry risk. | R51: 1,835 units are currently classified as high expiry risk.

Sheet Pivot Analysis
A1: FreshMart Sales KPI Summary
A3: Total Cost | B3: Total Revenue | C3: Gross Profit | D3: Units Sold | E3: Gross Margin %
A4: 3159.04 | B4: 4864.58 | C4: 1705.54 | D4: 711 | E4: =C4/B4 -> 0.35060375
A6: Sales Performance by Product Category | F6: Sales Performance by Store Region
A8: Row Labels | B8: Total Revenue | F8: Row Labels | G8: Total Revenue | H8: Units Sold | I8: Gross Profit
A9: Dairy | B9: 4864.58 | F9: West | G9: 4864.58 | H9: 711 | I9: 1705.54
A10: Grand Total | B10: 4864.58 | F10: Grand Total | G10: 4864.58 | H10: 711 | I10: 1705.54
A20: Waste and Shrinkage Summary | F20: Loss Performance by Product Category
A22: Row Labels | B22: Total Loss Value | C22: Units Lost | F22: Row Labels | G22: Total loss Value | H22: Units Lost
A23: Operational Waste | B23: 179.41 | C23: 44 | F23: Dairy | G23: 207.36 | H23: 56
A24: Shrinkage | B24: 27.95 | C24: 12 | F24: Grand Total | G24: 207.36 | H24: 56
A25: Grand Total | B25: 207.36 | C25: 56
A36: Markdown Performance by Batch Type
A38: Row Labels | B38: Markdown Revenue | C38: Units Marked Down | D38: Units Sold | E38: Unsold Units | F38: Lost Full-Price Value | G38: Potential Full-Price Value | H38: Markdown Sell-Through % | I38: Unsold Rate % | J38: Markdown Recovery %
A39: Standard Markdown | B39: 490.58 | C39: 208 | D39: 122 | E39: 86 | F39: 691.38 | G39: 1181.96 | H39: =D39/C39 -> 0.58653846 | I39: =E39/C39 -> 0.41346154 | J39: =B39/G39 -> 0.41505635
A40: Early Markdown | B40: 283.55 | C40: 75 | D40: 55 | E40: 20 | F40: 139.38 | G40: 422.93 | H40: =D40/C40 -> 0.73333333 | I40: =E40/C40 -> 0.26666667 | J40: =B40/G40 -> 0.67044192
A41: Late Markdown | B41: 67.18 | C41: 47 | D41: 21 | E41: 26 | F41: 210.57 | G41: 277.75 | H41: =D41/C41 -> 0.44680851 | I41: =E41/C41 -> 0.55319149 | J41: =B41/G41 -> 0.24187219
A42: Grand Total | B42: 841.31 | C42: 330 | D42: 198 | E42: 132 | F42: 1041.33 | G42: 1882.64 | H42: =D42/C42 -> 0.6 | I42: =E42/C42 -> 0.4 | J42: =B42/G42 -> 0.44687779
A45: Supplier Performance Analysis
A47: Row Labels | B47: Ordered Units | C47: Delivered Units | D47: Damaged Units | E47: Short-Supplied Units | F47: Total Delay Days | G47: Total Deliveries | H47: Fill Rate % | I47: Damage Rate % | J47: Short-Supply Rate % | K47: Average Delay Days
A48: FreshPack Dairy | B48: 1016 | C48: 946 | D48: 0 | E48: 70 | F48: 0 | G48: 8 | H48: =C48/B48 -> 0.93110236 | I48: =D48/C48 -> 0 | J48: =E48/B48 -> 0.068897638 | K48: =F48/G48 -> 0
A49: Southern Dairy Group | B49: 438 | C49: 403 | D49: 0 | E49: 35 | F49: 7 | G49: 4 | H49: =C49/B49 -> 0.92009132 | I49: =D49/C49 -> 0 | J49: =E49/B49 -> 0.079908676 | K49: =F49/G49 -> 1.75
A50: Grand Total | B50: 1454 | C50: 1349 | D50: 0 | E50: 105 | F50: 7 | G50: 12 | H50: =C50/B50 -> 0.92778542 | I50: =D50/C50 -> 0 | J50: =E50/B50 -> 0.07221458 | K50: =F50/G50 -> 0.58333333
H51: =C51/B51 -> #DIV/0! | I51: =D51/C51 -> #DIV/0! | J51: =E51/B51 -> #DIV/0! | K51: =F51/G51 -> #DIV/0!
H52: =C52/B52 -> #DIV/0! | I52: =D52/C52 -> #DIV/0! | J52: =E52/B52 -> #DIV/0! | K52: =F52/G52 -> #DIV/0!
H53: =C53/B53 -> #DIV/0! | I53: =D53/C53 -> #DIV/0! | J53: =E53/B53 -> #DIV/0! | K53: =F53/G53 -> #DIV/0!
H54: =C54/B54 -> #DIV/0! | I54: =D54/C54 -> #DIV/0! | J54: =E54/B54 -> #DIV/0! | K54: =F54/G54 -> #DIV/0!
H55: =C55/B55 -> #DIV/0! | I55: =D55/C55 -> #DIV/0! | J55: =E55/B55 -> #DIV/0! | K55: =F55/G55 -> #DIV/0!
H56: =C56/B56 -> #DIV/0! | I56: =D56/C56 -> #DIV/0! | J56: =E56/B56 -> #DIV/0! | K56: =F56/G56 -> #DIV/0!
H57: =C57/B57 -> #DIV/0! | I57: =D57/C57 -> #DIV/0! | J57: =E57/B57 -> #DIV/0! | K57: =F57/G57 -> #DIV/0!
H58: =C58/B58 -> #DIV/0! | I58: =D58/C58 -> #DIV/0! | J58: =E58/B58 -> #DIV/0! | K58: =F58/G58 -> #DIV/0!
H59: =C59/B59 -> #DIV/0! | I59: =D59/C59 -> #DIV/0! | J59: =E59/B59 -> #DIV/0! | K59: =F59/G59 -> #DIV/0!
H60: =C60/B60 -> #DIV/0! | I60: =D60/C60 -> #DIV/0! | J60: =E60/B60 -> #DIV/0! | K60: =F60/G60 -> #DIV/0!
A67: Inventory Analysis
A69: Inventory Snapshot Date | B69: 6/29/2026
A71: Expiry_Risk_Flag | B71: Category | C71: System Stock | D71: Actual Stock | E71: Recorded Waste Units | F71: Stock Count Variance
A72: High Risk | B72: Dairy | C72: 102 | D72: 102 | E72: 4 | F72: 0
A73: Medium Risk | B73: Dairy | C73: 65 | D73: 65 | E73: 3 | F73: 0
A74: Low Risk | B74: Dairy | C74: 280 | D74: 280 | E74: 0 | F74: 0
A75: Grand Total | C75: 447 | D75: 447 | E75: 7 | F75: 0

Sheet Dashboard Support
A1: Row Labels | B1: Total Revenue | F1: Row Labels | G1: Total Revenue
A2: Dairy | B2: 4864.58 | F2: West | G2: 4864.58
A15: Row Labels | B15: Loss Value | F15: Row Labels | G15: Markdown Sell-Through % | H15: Markdown Recovery %
A16: Dairy | B16: 207.36 | F16: Early Markdown | G16: 0.73333333 | H16: 0.67044192
F17: Standard Markdown | G17: 0.58653846 | H17: 0.41505635
F18: Late Markdown | G18: 0.44680851 | H18: 0.24187219
A19: Supplier Fill Rate % | B19: Short-Supply Rate %
A20: 0.94227269 | B20: 0.057727315
